[
    {
        "beeps": {
            "additionalCriteria": false,
            "dailyBeeps": 1,
            "importantMomentsOnly": false
        },
        "days": 0,
        "description": "To je testni projekt, da se lahko za\u010dnejo igrati z aplikacijo",
        "descriptive": true,
        "email": "sarajaksa@sarajaksa.eu",
        "end": "2020-12-31",
        "id": "sara2019testni",
        "location": false,
        "name": "Testni projekt",
        "organization": "",
        "password": "",
        "privacy": "nobenih",
        "questions": [
            {
                "context": false,
                "current": 1,
                "id": 1,
                "question": "Ali si prisoten v trenutku?",
                "type": "Binary"
            },
            {
                "context": true,
                "current": 1,
                "id": 2,
                "question": "S kom s trenutno?",
                "type": "Tags"
            },
            {
                "context": false,
                "current": 1,
                "id": 3,
                "question": "Kako pozitivno se trenutno po\u010duti\u0161?",
                "type": "Slider"
            }
        ],
        "researcher": "Sara Jak\u0161a",
        "share": false,
        "start": "2019-01-23",
        "subjectId": null
    }
]